llm_tools/__init__.py
llm_tools/exceptions.py
llm_tools/openai/prompt.py
llm_tools/parser.py
llm_tools/utils.py
llm_commons-0.0.1.dist-info/METADATA
llm_commons-0.0.1.dist-info/WHEEL
llm_commons-0.0.1.dist-info/RECORD
