Metadata-Version: 2.1
Name: llm-commons
Version: 0.0.1
Summary: A Python wrapper for managing OpenAI API and other LLM models.
License: MIT
Author: Aivin V. Solatorio
Author-email: avsolatorio@gmail.com
Requires-Python: >=3.10,<4.0
Classifier: License :: OSI Approved :: MIT License
Classifier: Programming Language :: Python :: 3
Classifier: Programming Language :: Python :: 3.10
Classifier: Programming Language :: Python :: 3.11
Requires-Dist: backoff (>=2.2.1,<3.0.0)
Requires-Dist: jinja2 (>=3.1.2,<4.0.0)
Requires-Dist: openai (>=1.3.8,<2.0.0)
Requires-Dist: tiktoken (>=0.5.2,<0.6.0)
